LICENSE.txt
MANIFEST.in
README.md
setup.cfg
setup.py
share_file_qr.egg-info/PKG-INFO
share_file_qr.egg-info/SOURCES.txt
share_file_qr.egg-info/dependency_links.txt
share_file_qr.egg-info/entry_points.txt
share_file_qr.egg-info/requires.txt
share_file_qr.egg-info/top_level.txt
sharefileqr/__init__.py
sharefileqr/cli.py
sharefileqr/core.py
sharefileqr/handlers.py
sharefileqr/network.py
sharefileqr/qrcodes.py