Metadata-Version: 2.1
Name: share-file-qr
Version: 0.2.0
Summary: Share files from the terminal of your computer to a smartphone by scanning a QR code.
Home-page: https://github.com/pwalch/share-file-qr
Author: Pierre Walch
Author-email: contact@pwal.ch
License: GPLv3
Keywords: qr code smartphone share file
Platform: UNKNOWN
Classifier: Development Status :: 3 - Alpha
Classifier: Intended Audience :: Developers
Classifier: Topic :: Communications :: File Sharing
Classifier: License :: OSI Approved :: GNU General Public License v3 (GPLv3)
Classifier: Programming Language :: Python :: 3.9
Requires-Python: >=3.9
License-File: LICENSE.txt
